{
  "description": "Mirrors the artifacts table (migrations 001 + 005).",
  "properties": {
    "artifact_id": {
      "anyOf": [
        {
          "type": "integer"
        },
        {
          "type": "null"
        }
      ],
      "default": null,
      "title": "Artifact Id"
    },
    "org_id": {
      "title": "Org Id",
      "type": "string"
    },
    "job_id": {
      "anyOf": [
        {
          "type": "string"
        },
        {
          "type": "null"
        }
      ],
      "default": null,
      "title": "Job Id"
    },
    "artifact_type": {
      "title": "Artifact Type",
      "type": "string"
    },
    "path": {
      "anyOf": [
        {
          "type": "string"
        },
        {
          "type": "null"
        }
      ],
      "default": null,
      "title": "Path"
    },
    "metadata_json": {
      "default": "{}",
      "title": "Metadata Json",
      "type": "string"
    },
    "stale": {
      "default": false,
      "title": "Stale",
      "type": "boolean"
    },
    "degraded": {
      "default": false,
      "title": "Degraded",
      "type": "boolean"
    },
    "created_at": {
      "anyOf": [
        {
          "type": "string"
        },
        {
          "type": "null"
        }
      ],
      "default": null,
      "title": "Created At"
    }
  },
  "required": [
    "org_id",
    "artifact_type"
  ],
  "title": "Artifact",
  "type": "object"
}
